extorch/VERSION
extorch/__init__.py
extorch/adversarial/__init__.py
extorch/adversarial/base.py
extorch/adversarial/gradient_based.py
extorch/nn/__init__.py
extorch/nn/functional.py
extorch/nn/init.py
extorch/nn/utils.py
extorch/nn/modules/__init__.py
extorch/nn/modules/auxiliary.py
extorch/nn/modules/block.py
extorch/nn/modules/loss.py
extorch/nn/modules/mlp.py
extorch/nn/modules/operation.py
extorch/nn/optim/__init__.py
extorch/nn/optim/lr_scheduler.py
extorch/utils/__init__.py
extorch/utils/common.py
extorch/utils/exception.py
extorch/utils/logger.py
extorch/utils/stats.py
extorch/utils/visual.py
extorch/vision/__init__.py
extorch/vision/functional.py
extorch/vision/paired_transform.py
extorch/vision/transforms.py
extorch/vision/dataset/PennFudan.py
extorch/vision/dataset/__init__.py
extorch/vision/dataset/base.py
extorch/vision/dataset/cifar10.py
extorch/vision/dataset/cifar100.py
extorch/vision/dataset/fashion_mnist.py
extorch/vision/dataset/mnist.py
extorch/vision/dataset/svhn.py
extorch/vision/dataset/tiny_imagenet.py
extorch/vision/dataset/voc.py
extorch/vision/transforms/__init__.py
extorch/vision/transforms/detection.py
extorch/vision/transforms/functional.py
extorch/vision/transforms/paired_transform.py
extorch/vision/transforms/segmentation.py
extorch/vision/transforms/transforms.py
extorch-1.0.4.dist-info/LICENSE
extorch-1.0.4.dist-info/METADATA
extorch-1.0.4.dist-info/WHEEL
extorch-1.0.4.dist-info/top_level.txt
extorch-1.0.4.dist-info/RECORD
