Metadata-Version: 2.1
Name: extorch
Version: 1.0.4
Summary: An useful extension library of PyTorch.
Home-page: https://github.com/A-LinCui/Extorch
Author: Junbo Zhao
Author-email: zhaojunbo2012@sina.cn
License: MIT License
Keywords: PyTorch
Platform: UNKNOWN
Classifier: Intended Audience :: Developers
Classifier: Intended Audience :: Science/Research
Classifier: License :: OSI Approved :: MIT License
Classifier: Programming Language :: Python :: 3
Classifier: Programming Language :: Python :: 3.6
Classifier: Programming Language :: Python :: 3.7
Classifier: Topic :: Scientific/Engineering :: Artificial Intelligence
License-File: LICENSE
Requires-Dist: pyyaml
Requires-Dist: ipdb
Requires-Dist: scikit-learn
Requires-Dist: numpy
Requires-Dist: torch
Requires-Dist: setuptools
Requires-Dist: torch (>=1.2.0)
Requires-Dist: torchvision (>=0.4.0)
Requires-Dist: matplotlib
Requires-Dist: pillow
